{
    "data": {
      "exploreList": {
        "edges": [
          {
            "node": {
              "address": "0xd53511218e3742c0cb585ce058fac13219d5c1ad",
              "name": "mkxnmi",
              "createdAt": "2025-07-27T21:47:27",
              "creatorProfile": {
                "id": "R3JhcGhRTEFjY291bnRQcm9maWxlOjY4ODY5ZTVkN2U0OGIzODZiN2NjN2YxMg==",
                "followedEdges": {
                  "count": 0
                },
                "username": "mkxnmi",
                "socialAccounts": {
                  "farcaster": null,
                  "twitter": null
                }
              }
            }
          },
          {
            "node": {
              "address": "0x6391ffdfbb8b0051af274d8bec106b62352535f1",
              "name": "abundance99",
              "createdAt": "2025-07-27T21:47:21",
              "creatorProfile": {
                "id": "R3JhcGhRTEFjY291bnRQcm9maWxlOjY2ZmMyMWUwZGU0YTdiZTI2ODljZjUzZQ==",
                "followedEdges": {
                  "count": 28
                },
                "username": "abundance99",
                "socialAccounts": {
                  "farcaster": null,
                  "twitter": {
                    "displayName": "Abundance99",
                    "username": "Raphmoore2"
                  }
                }
              }
            }
          },
          {
            "node": {
              "address": "0x6ca029f9a6b1505cadaf161f751ed22f507bf899",
              "name": "rbthreeek",
              "createdAt": "2025-07-27T21:47:17",
              "creatorProfile": {
                "id": "R3JhcGhRTEFjY291bnRQcm9maWxlOjY4ODY5ZTUyYmY1MjFkYmNhN2U5MThkNg==",
                "followedEdges": {
                  "count": 0
                },
                "username": "rbthreeek",
                "socialAccounts": {
                  "farcaster": null,
                  "twitter": null
                }
              }
            }
          },
          {
            "node": {
              "address": "0xa01200f1ab272536accc7ba615e9ae47f7921d96",
              "name": "r_leshner",
              "createdAt": "2025-07-27T21:47:15",
              "creatorProfile": {
                "id": "R3JhcGhRTEFjY291bnRQcm9maWxlOjY4ODY5ZTNhZGVhN2Q1MzkxOGU4YWJjMg==",
                "followedEdges": {
                  "count": 0
                },
                "username": "r_leshner",
                "socialAccounts": {
                  "farcaster": null,
                  "twitter": null
                }
              }
            }
          },
          {
            "node": {
              "address": "0xd8d4d7a62750de85152f299332a83ae4d8c351bc",
              "name": "laksh_ghai",
              "createdAt": "2025-07-27T21:47:11",
              "creatorProfile": {
                "id": "R3JhcGhRTEFjY291bnRQcm9maWxlOjY4ODY5ZGU5MzM0YTNkMTQ5MTAyYzBjYQ==",
                "followedEdges": {
                  "count": 0
                },
                "username": "laksh_ghai",
                "socialAccounts": {
                  "farcaster": null,
                  "twitter": null
                }
              }
            }
          },
          {
            "node": {
              "address": "0x0aba171fb7749a25e9ae41eea7335f87daed5dde",
              "name": "xerio",
              "createdAt": "2025-07-27T21:47:07",
              "creatorProfile": {
                "id": "R3JhcGhRTEFjY291bnRQcm9maWxlOjY4ODY5ZTRiYzc3NDZiOTg4YTBjZjU4YQ==",
                "followedEdges": {
                  "count": 0
                },
                "username": "xerio",
                "socialAccounts": {
                  "farcaster": null,
                  "twitter": null
                }
              }
            }
          },
          {
            "node": {
              "address": "0x1e1b737a802916849d22b7ea39f5adb05f6ad703",
              "name": "badr624",
              "createdAt": "2025-07-27T21:47:03",
              "creatorProfile": {
                "id": "R3JhcGhRTEFjY291bnRQcm9maWxlOjY4ODY5ZTI0M2FmZjdjYTQ4ZDVhYjcyMw==",
                "followedEdges": {
                  "count": 0
                },
                "username": "badr624",
                "socialAccounts": {
                  "farcaster": null,
                  "twitter": null
                }
              }
            }
          },
          {
            "node": {
              "address": "0x8b209fb81f6404e20e4b7943539e3adcd04448bf",
              "name": "tattoo80",
              "createdAt": "2025-07-27T21:46:55",
              "creatorProfile": {
                "id": "R3JhcGhRTEFjY291bnRQcm9maWxlOjY1NTVmMTlhZWU4ZTUwN2Q3NWVmZWY5Nw==",
                "followedEdges": {
                  "count": 356
                },
                "username": "tattoo80",
                "socialAccounts": {
                  "farcaster": {
                    "displayName": "L Dornelas",
                    "username": "tattoo80eth"
                  },
                  "twitter": {
                    "displayName": "DornelasL",
                    "username": "lukinhadornelas"
                  }
                }
              }
            }
          },
          {
            "node": {
              "address": "0x3c0e2e635737af73d2b4c636fb732705b786f6de",
              "name": "dszora",
              "createdAt": "2025-07-27T21:46:55",
              "creatorProfile": {
                "id": "R3JhcGhRTEFjY291bnRQcm9maWxlOjY4ODY5ZTNmMzM0YTNkMTQ5MTAyYzBkNA==",
                "followedEdges": {
                  "count": 0
                },
                "username": "dszora",
                "socialAccounts": {
                  "farcaster": null,
                  "twitter": null
                }
              }
            }
          },
          {
            "node": {
              "address": "0xdfdad6675e5d9c0e4b39035565225e3ee94d2f69",
              "name": "roshanpillai",
              "createdAt": "2025-07-27T21:46:55",
              "creatorProfile": {
                "id": "R3JhcGhRTEFjY291bnRQcm9maWxlOjY4ODY5ZTQwZWFhZTA0YmZkYTgwYmI0Ng==",
                "followedEdges": {
                  "count": 0
                },
                "username": "roshanpillai",
                "socialAccounts": {
                  "farcaster": null,
                  "twitter": null
                }
              }
            }
          },
          {
            "node": {
              "address": "0xfce45472ec01590b811d05ecefa7b6956b3a324f",
              "name": "etherizon",
              "createdAt": "2025-07-27T21:46:53",
              "creatorProfile": {
                "id": "R3JhcGhRTEFjY291bnRQcm9maWxlOjY3YzY3MTUyZDU0OGI5NTIzYjY3M2JjMQ==",
                "followedEdges": {
                  "count": 2
                },
                "username": "etherizon",
                "socialAccounts": {
                  "farcaster": null,
                  "twitter": null
                }
              }
            }
          },
          {
            "node": {
              "address": "0x56dbb3ddbd911443f246458475b1dd40b2828829",
              "name": "universecok100",
              "createdAt": "2025-07-27T21:46:53",
              "creatorProfile": {
                "id": "R3JhcGhRTEFjY291bnRQcm9maWxlOjY4ODY5ZTNiZDk1MGY0NTcwNjk2NTA0NQ==",
                "followedEdges": {
                  "count": 0
                },
                "username": "universecok100",
                "socialAccounts": {
                  "farcaster": null,
                  "twitter": null
                }
              }
            }
          },
          {
            "node": {
              "address": "0x3f372265f62782a7ae9d24ca5e4488e73bc6ef21",
              "name": "seyf",
              "createdAt": "2025-07-27T21:46:51",
              "creatorProfile": {
                "id": "R3JhcGhRTEFjY291bnRQcm9maWxlOjY4ODY5ZTNkYzc3NDZiOTg4YTBjZjU4Nw==",
                "followedEdges": {
                  "count": 0
                },
                "username": "seyf",
                "socialAccounts": {
                  "farcaster": null,
                  "twitter": null
                }
              }
            }
          },
          {
            "node": {
              "address": "0x50f0e14a1bb09a43f8acd5004c61f4c8efe8acac",
              "name": "fineryblaze",
              "createdAt": "2025-07-27T21:46:41",
              "creatorProfile": {
                "id": "R3JhcGhRTEFjY291bnRQcm9maWxlOjY4ODY5OTQxZmZlMzczM2ZlNTQyYWM2MQ==",
                "followedEdges": {
                  "count": 1
                },
                "username": "fineryblaze",
                "socialAccounts": {
                  "farcaster": null,
                  "twitter": {
                    "displayName": "@BlazeFinery | 𝔽rAI",
                    "username": "FineryBlaze"
                  }
                }
              }
            }
          },
          {
            "node": {
              "address": "0xe3763095680249293d2de66b88a654bc17f97d45",
              "name": "lilybilly",
              "createdAt": "2025-07-27T21:46:37",
              "creatorProfile": {
                "id": "R3JhcGhRTEFjY291bnRQcm9maWxlOjY4ODY5ZGM5OTYwMDRhYWU5ODU3YTNkOA==",
                "followedEdges": {
                  "count": 0
                },
                "username": "lilybilly",
                "socialAccounts": {
                  "farcaster": null,
                  "twitter": null
                }
              }
            }
          },
          {
            "node": {
              "address": "0xc39c1ad62282e91693de78c0ea25112a95de0bcd",
              "name": "altereg0",
              "createdAt": "2025-07-27T21:46:35",
              "creatorProfile": {
                "id": "R3JhcGhRTEFjY291bnRQcm9maWxlOjY4ODY5ZTJjOTYwMDRhYWU5ODU3YTNkZg==",
                "followedEdges": {
                  "count": 0
                },
                "username": "altereg0",
                "socialAccounts": {
                  "farcaster": null,
                  "twitter": null
                }
              }
            }
          },
          {
            "node": {
              "address": "0x6da23154e5ba0a2952fb2af0d019dfe2b5acab47",
              "name": "fabric",
              "createdAt": "2025-07-27T21:46:25",
              "creatorProfile": {
                "id": "R3JhcGhRTEFjY291bnRQcm9maWxlOjY4ODY5ZGU4Mzk0YTExOTQ3MWIzNTMwMA==",
                "followedEdges": {
                  "count": 1
                },
                "username": "fabric",
                "socialAccounts": {
                  "farcaster": {
                    "displayName": "Gladys Bee",
                    "username": "gladysdab"
                  },
                  "twitter": {
                    "displayName": "Matchaxyz on zora",
                    "username": "yosuaeth"
                  }
                }
              }
            }
          },
          {
            "node": {
              "address": "0x2006009f7187006a7226b1cad460acb687542a2a",
              "name": "tonicinu",
              "createdAt": "2025-07-27T21:46:23",
              "creatorProfile": {
                "id": "R3JhcGhRTEFjY291bnRQcm9maWxlOjY4ODY5ZGFlN2U0OGIzODZiN2NjN2YwOQ==",
                "followedEdges": {
                  "count": 0
                },
                "username": "tonicinu",
                "socialAccounts": {
                  "farcaster": null,
                  "twitter": null
                }
              }
            }
          },
          {
            "node": {
              "address": "0xe71d976542913dbaa827d9da359af1d8d1e92c9f",
              "name": "pikka",
              "createdAt": "2025-07-27T21:46:15",
              "creatorProfile": {
                "id": "R3JhcGhRTEFjY291bnRQcm9maWxlOjY1ZTE3NzY0M2RiOWVkYjgyZjA3YmMzNw==",
                "followedEdges": {
                  "count": 10
                },
                "username": "pikka",
                "socialAccounts": {
                  "farcaster": null,
                  "twitter": null
                }
              }
            }
          },
          {
            "node": {
              "address": "0x554396d1e12a8804589f9f83a58a204b7fa64903",
              "name": "oliviadrozdz",
              "createdAt": "2025-07-27T21:46:09",
              "creatorProfile": {
                "id": "R3JhcGhRTEFjY291bnRQcm9maWxlOjY4ODY5ZTEwM2FmZjdjYTQ4ZDVhYjcyMA==",
                "followedEdges": {
                  "count": 0
                },
                "username": "oliviadrozdz",
                "socialAccounts": {
                  "farcaster": null,
                  "twitter": null
                }
              }
            }
          },
          {
            "node": {
              "address": "0x9c18dd4309137eccd588f2d4c4e3f4c8ab1be7f0",
              "name": "toot",
              "createdAt": "2025-07-27T21:46:03",
              "creatorProfile": {
                "id": "R3JhcGhRTEFjY291bnRQcm9maWxlOjY4ODY5ZTBiYzc3NDZiOTg4YTBjZjU4NA==",
                "followedEdges": {
                  "count": 0
                },
                "username": "toot",
                "socialAccounts": {
                  "farcaster": null,
                  "twitter": null
                }
              }
            }
          },
          {
            "node": {
              "address": "0xc66db4b1a0a3a5b20b6b472813aecc413b6f4406",
              "name": "degentoonz",
              "createdAt": "2025-07-27T21:46:01",
              "creatorProfile": {
                "id": "R3JhcGhRTEFjY291bnRQcm9maWxlOjY4ODY5ZGRjZDk1MGY0NTcwNjk2NTA0MQ==",
                "followedEdges": {
                  "count": 0
                },
                "username": "degentoonz",
                "socialAccounts": {
                  "farcaster": null,
                  "twitter": null
                }
              }
            }
          },
          {
            "node": {
              "address": "0xc531c25a6446ee36b8747a0f25216627ce3ad758",
              "name": "neyan",
              "createdAt": "2025-07-27T21:46:01",
              "creatorProfile": {
                "id": "R3JhcGhRTEFjY291bnRQcm9maWxlOjY4ODY5ZGZiZGVhN2Q1MzkxOGU4YWJiYw==",
                "followedEdges": {
                  "count": 0
                },
                "username": "neyan",
                "socialAccounts": {
                  "farcaster": null,
                  "twitter": null
                }
              }
            }
          },
          {
            "node": {
              "address": "0x191a1cd241315628be6984c1fca300e1ec5de507",
              "name": "snoopymetax",
              "createdAt": "2025-07-27T21:45:59",
              "creatorProfile": {
                "id": "R3JhcGhRTEFjY291bnRQcm9maWxlOjY4ODY5ZGY4N2U0OGIzODZiN2NjN2YwZA==",
                "followedEdges": {
                  "count": 4
                },
                "username": "snoopymetax",
                "socialAccounts": {
                  "farcaster": null,
                  "twitter": {
                    "displayName": "Snoopy🌱",
                    "username": "snoopymetax"
                  }
                }
              }
            }
          },
          {
            "node": {
              "address": "0xed9b8c71620a16c5f6a21c44cee030b241328ace",
              "name": "shibasea",
              "createdAt": "2025-07-27T21:45:59",
              "creatorProfile": {
                "id": "R3JhcGhRTEFjY291bnRQcm9maWxlOjY4ODY5ZGY1OWI0MTEyMmRjNzZjZjNkYg==",
                "followedEdges": {
                  "count": 0
                },
                "username": "shibasea",
                "socialAccounts": {
                  "farcaster": null,
                  "twitter": null
                }
              }
            }
          },
          {
            "node": {
              "address": "0x1d1c4296f6746dff6accde5aaa91bbbab76c458d",
              "name": "cryptobabe5969",
              "createdAt": "2025-07-27T21:45:55",
              "creatorProfile": {
                "id": "R3JhcGhRTEFjY291bnRQcm9maWxlOjY4ODY5ZTAzMzM0YTNkMTQ5MTAyYzBkMQ==",
                "followedEdges": {
                  "count": 0
                },
                "username": "cryptobabe5969",
                "socialAccounts": {
                  "farcaster": null,
                  "twitter": null
                }
              }
            }
          },
          {
            "node": {
              "address": "0x8d93c12074e38a58e0f3b987be82e9105663094a",
              "name": "dtdddd",
              "createdAt": "2025-07-27T21:45:43",
              "creatorProfile": {
                "id": "R3JhcGhRTEFjY291bnRQcm9maWxlOjY4ODY5ZGY3Mzk0YTExOTQ3MWIzNTMwMw==",
                "followedEdges": {
                  "count": 0
                },
                "username": "dtdddd",
                "socialAccounts": {
                  "farcaster": null,
                  "twitter": null
                }
              }
            }
          },
          {
            "node": {
              "address": "0xb5c38e20fcf309f9c2c3dedafe5dfb0d6ca42887",
              "name": "kami14",
              "createdAt": "2025-07-27T21:45:41",
              "creatorProfile": {
                "id": "R3JhcGhRTEFjY291bnRQcm9maWxlOjY4ODY5ZGY0MzM0YTNkMTQ5MTAyYzBjZA==",
                "followedEdges": {
                  "count": 0
                },
                "username": "kami14",
                "socialAccounts": {
                  "farcaster": null,
                  "twitter": null
                }
              }
            }
          },
          {
            "node": {
              "address": "0x783affa8f9a3d7cf05eeb1e012dabdd8c1712632",
              "name": "alexdanco",
              "createdAt": "2025-07-27T21:45:41",
              "creatorProfile": {
                "id": "R3JhcGhRTEFjY291bnRQcm9maWxlOjY4ODY5ZGY1M2FmZjdjYTQ4ZDVhYjcxZA==",
                "followedEdges": {
                  "count": 0
                },
                "username": "alexdanco",
                "socialAccounts": {
                  "farcaster": null,
                  "twitter": null
                }
              }
            }
          },
          {
            "node": {
              "address": "0xe83a2a14034f3f44dadcee2c9bb33bf623fa26e4",
              "name": "perlnzora",
              "createdAt": "2025-07-27T21:45:39",
              "creatorProfile": {
                "id": "R3JhcGhRTEFjY291bnRQcm9maWxlOjY4ODY5ZGJiZWFhZTA0YmZkYTgwYmI0MA==",
                "followedEdges": {
                  "count": 1
                },
                "username": "perlnzora",
                "socialAccounts": {
                  "farcaster": null,
                  "twitter": null
                }
              }
            }
          },
          {
            "node": {
              "address": "0x1820171a6a8203a4ca447c9dd0a4c1397a5d502a",
              "name": "mangunzalo",
              "createdAt": "2025-07-27T21:45:33",
              "creatorProfile": {
                "id": "R3JhcGhRTEFjY291bnRQcm9maWxlOjY2NmFhYzVhNWJlZDZhMmFmMDQ1ZmYwZA==",
                "followedEdges": {
                  "count": 10
                },
                "username": "mangunzalo",
                "socialAccounts": {
                  "farcaster": {
                    "displayName": "Alaga Abubakar Ahmed",
                    "username": "abukhalifa"
                  },
                  "twitter": null
                }
              }
            }
          },
          {
            "node": {
              "address": "0x7f46cff70ff848bd8f3909b0b6465d04126a4a82",
              "name": "ericxtang",
              "createdAt": "2025-07-27T21:45:31",
              "creatorProfile": {
                "id": "R3JhcGhRTEFjY291bnRQcm9maWxlOjY3YjgwNjZkY2NhY2YwZjExMmMyNDYxYg==",
                "followedEdges": {
                  "count": 1
                },
                "username": "ericxtang",
                "socialAccounts": {
                  "farcaster": null,
                  "twitter": null
                }
              }
            }
          },
          {
            "node": {
              "address": "0xeb8513956d9bd9676b949acd09f2a9279df81838",
              "name": "bok",
              "createdAt": "2025-07-27T21:45:19",
              "creatorProfile": {
                "id": "R3JhcGhRTEFjY291bnRQcm9maWxlOjY4ODY5ZGQ0M2E4ZjhhNDUxNDA4M2M1Mw==",
                "followedEdges": {
                  "count": 0
                },
                "username": "bok",
                "socialAccounts": {
                  "farcaster": null,
                  "twitter": null
                }
              }
            }
          },
          {
            "node": {
              "address": "0x4119ef6c9310b3c2e67743cf622b4d0b69ff6e22",
              "name": "emgems",
              "createdAt": "2025-07-27T21:45:19",
              "creatorProfile": {
                "id": "R3JhcGhRTEFjY291bnRQcm9maWxlOjY4ODY5ZGRhM2E4ZjhhNDUxNDA4M2M1Nw==",
                "followedEdges": {
                  "count": 0
                },
                "username": "emgems",
                "socialAccounts": {
                  "farcaster": null,
                  "twitter": null
                }
              }
            }
          },
          {
            "node": {
              "address": "0xfc3d2679192ad8576c2c57051b22ad4e7a454418",
              "name": "sipani",
              "createdAt": "2025-07-27T21:45:17",
              "creatorProfile": {
                "id": "R3JhcGhRTEFjY291bnRQcm9maWxlOjY4MTc2NzdmYzdhOTgyZmI4MDE1NmU2Ng==",
                "followedEdges": {
                  "count": 0
                },
                "username": "sipani",
                "socialAccounts": {
                  "farcaster": null,
                  "twitter": null
                }
              }
            }
          },
          {
            "node": {
              "address": "0xd50ca240fd53f3c9e08ae91188435a93051153b0",
              "name": "tcb4real",
              "createdAt": "2025-07-27T21:45:05",
              "creatorProfile": {
                "id": "R3JhcGhRTEFjY291bnRQcm9maWxlOjY4ODY5ZGQyMzk0YTExOTQ3MWIzNTJmZA==",
                "followedEdges": {
                  "count": 0
                },
                "username": "tcb4real",
                "socialAccounts": {
                  "farcaster": null,
                  "twitter": null
                }
              }
            }
          },
          {
            "node": {
              "address": "0xa573e4ed1982ede37dac0af3f89ca769aa009ea5",
              "name": "yinyangtaino",
              "createdAt": "2025-07-27T21:45:05",
              "creatorProfile": {
                "id": "R3JhcGhRTEFjY291bnRQcm9maWxlOjY4ODY5ZGJmNDI2OGJjNjQwYzEwNjkyMA==",
                "followedEdges": {
                  "count": 0
                },
                "username": "yinyangtaino",
                "socialAccounts": {
                  "farcaster": null,
                  "twitter": null
                }
              }
            }
          },
          {
            "node": {
              "address": "0x24aa38bc34667d08a67460f51215759ab60ce28f",
              "name": "form",
              "createdAt": "2025-07-27T21:45:01",
              "creatorProfile": {
                "id": "R3JhcGhRTEFjY291bnRQcm9maWxlOjY4ODY5ZGE3M2FmZjdjYTQ4ZDVhYjcxOA==",
                "followedEdges": {
                  "count": 1
                },
                "username": "form",
                "socialAccounts": {
                  "farcaster": null,
                  "twitter": {
                    "displayName": "Mei",
                    "username": "0xboulevard"
                  }
                }
              }
            }
          },
          {
            "node": {
              "address": "0x5f71866e8db886fb6a4968b5be89945d12a02096",
              "name": "warrenzora",
              "createdAt": "2025-07-27T21:45:01",
              "creatorProfile": {
                "id": "R3JhcGhRTEFjY291bnRQcm9maWxlOjY4ODY5ZDgzM2E4ZjhhNDUxNDA4M2M1MA==",
                "followedEdges": {
                  "count": 0
                },
                "username": "warrenzora",
                "socialAccounts": {
                  "farcaster": null,
                  "twitter": null
                }
              }
            }
          },
          {
            "node": {
              "address": "0x61f8a408c9a7110914c84db3bc5d11fe1eb3b3c7",
              "name": "pap0nt",
              "createdAt": "2025-07-27T21:44:55",
              "creatorProfile": {
                "id": "R3JhcGhRTEFjY291bnRQcm9maWxlOjY1ZTRjMDQxN2JiYTFlOGZlNGYxMTI1OQ==",
                "followedEdges": {
                  "count": 7
                },
                "username": "pap0nt",
                "socialAccounts": {
                  "farcaster": null,
                  "twitter": {
                    "displayName": "mystic pap0nt🔮",
                    "username": "pap0nt"
                  }
                }
              }
            }
          },
          {
            "node": {
              "address": "0x569ec1f553ec2d5e19b89a999a57d033c1f24961",
              "name": "eklirion",
              "createdAt": "2025-07-27T21:44:49",
              "creatorProfile": {
                "id": "R3JhcGhRTEFjY291bnRQcm9maWxlOjY4ODY5ZGFiN2U0OGIzODZiN2NjN2YwNQ==",
                "followedEdges": {
                  "count": 0
                },
                "username": "eklirion",
                "socialAccounts": {
                  "farcaster": null,
                  "twitter": null
                }
              }
            }
          },
          {
            "node": {
              "address": "0x225c7a08fd0a93cbd3f4f9d107c91aa4c7ece521",
              "name": "sportpsychology",
              "createdAt": "2025-07-27T21:44:49",
              "creatorProfile": {
                "id": "R3JhcGhRTEFjY291bnRQcm9maWxlOjY1MWVlODE2MGFkZGU0Y2JkODljMDdjYg==",
                "followedEdges": {
                  "count": 124
                },
                "username": "sportpsychology",
                "socialAccounts": {
                  "farcaster": {
                    "displayName": "Joker",
                    "username": "joker6"
                  },
                  "twitter": {
                    "displayName": "Joker6",
                    "username": "Joker_M33"
                  }
                }
              }
            }
          },
          {
            "node": {
              "address": "0x9cb07be499b33c92f71202f668fa6fd0bf9ae3be",
              "name": "goofyfun",
              "createdAt": "2025-07-27T21:44:49",
              "creatorProfile": {
                "id": "R3JhcGhRTEFjY291bnRQcm9maWxlOjY4ODY5ZGFhZGVhN2Q1MzkxOGU4YWJiOQ==",
                "followedEdges": {
                  "count": 1
                },
                "username": "goofyfun",
                "socialAccounts": {
                  "farcaster": null,
                  "twitter": {
                    "displayName": "Goofy",
                    "username": "goofydotfun"
                  }
                }
              }
            }
          },
          {
            "node": {
              "address": "0x5c3a9a5ea377297e61f62a60302156c978046849",
              "name": "maidaboi",
              "createdAt": "2025-07-27T21:44:45",
              "creatorProfile": {
                "id": "R3JhcGhRTEFjY291bnRQcm9maWxlOjY4ODY5ZGJhZDk1MGY0NTcwNjk2NTAzZQ==",
                "followedEdges": {
                  "count": 0
                },
                "username": "maidaboi",
                "socialAccounts": {
                  "farcaster": null,
                  "twitter": null
                }
              }
            }
          },
          {
            "node": {
              "address": "0x1017e5da0082cd89d8d4f8c236314525d5d0bb2c",
              "name": "angryzora",
              "createdAt": "2025-07-27T21:44:31",
              "creatorProfile": {
                "id": "R3JhcGhRTEFjY291bnRQcm9maWxlOjY4ODY5Y2E5ZWFhZTA0YmZkYTgwYmIzNw==",
                "followedEdges": {
                  "count": 0
                },
                "username": "angryzora",
                "socialAccounts": {
                  "farcaster": null,
                  "twitter": null
                }
              }
            }
          },
          {
            "node": {
              "address": "0xe61600dc374ed079ece6a8e2670f19f878e6dfd8",
              "name": "hamliavyi_ihor",
              "createdAt": "2025-07-27T21:44:29",
              "creatorProfile": {
                "id": "R3JhcGhRTEFjY291bnRQcm9maWxlOjY2Y2M1MTg4MjFkZjNlOTdjMTJkNTE1Yg==",
                "followedEdges": {
                  "count": 154
                },
                "username": "hamliavyi_ihor",
                "socialAccounts": {
                  "farcaster": {
                    "displayName": "Hamliavyi Ihor",
                    "username": "apache002"
                  },
                  "twitter": {
                    "displayName": "HAMI ꧁IP꧂",
                    "username": "hamliavyi_ihor"
                  }
                }
              }
            }
          },
          {
            "node": {
              "address": "0xdfac120ea954851e71a57422f5977d1dae88f164",
              "name": "nasahubble",
              "createdAt": "2025-07-27T21:44:27",
              "creatorProfile": {
                "id": "R3JhcGhRTEFjY291bnRQcm9maWxlOjY4ODY5ZGE3NDRhZGE0OGJlNmJmMjRjOQ==",
                "followedEdges": {
                  "count": 0
                },
                "username": "nasahubble",
                "socialAccounts": {
                  "farcaster": null,
                  "twitter": null
                }
              }
            }
          },
          {
            "node": {
              "address": "0x8f1cb73cf4e69a810a31daf3746a36e6b738045a",
              "name": "zorabullishh",
              "createdAt": "2025-07-27T21:44:25",
              "creatorProfile": {
                "id": "R3JhcGhRTEFjY291bnRQcm9maWxlOjY4ODY5ZDc1ZDk1MGY0NTcwNjk2NTAzOQ==",
                "followedEdges": {
                  "count": 0
                },
                "username": "zorabullishh",
                "socialAccounts": {
                  "farcaster": null,
                  "twitter": null
                }
              }
            }
          },
          {
            "node": {
              "address": "0xcf6df9671f88864ffc0b3ea04b54828a38a58194",
              "name": "wgmi",
              "createdAt": "2025-07-27T21:44:23",
              "creatorProfile": {
                "id": "R3JhcGhRTEFjY291bnRQcm9maWxlOjY4ODY5ZGEwN2U0OGIzODZiN2NjN2YwMg==",
                "followedEdges": {
                  "count": 0
                },
                "username": "wgmi",
                "socialAccounts": {
                  "farcaster": null,
                  "twitter": null
                }
              }
            }
          },
          {
            "node": {
              "address": "0x1413832d9ecd66477763f3a8a42717565c98b69e",
              "name": "yatirimcrypto",
              "createdAt": "2025-07-27T21:44:15",
              "creatorProfile": {
                "id": "R3JhcGhRTEFjY291bnRQcm9maWxlOjY1NmUzM2M5Zjg0NmYyYTQwZGRkODg3Mg==",
                "followedEdges": {
                  "count": 1
                },
                "username": "yatirimcrypto",
                "socialAccounts": {
                  "farcaster": null,
                  "twitter": null
                }
              }
            }
          },
          {
            "node": {
              "address": "0xaa35a19cfd7dc10d26bc32ed2d069966801e9894",
              "name": "maudie",
              "createdAt": "2025-07-27T21:43:59",
              "creatorProfile": {
                "id": "R3JhcGhRTEFjY291bnRQcm9maWxlOjY4ODY5ZDkwYmY1MjFkYmNhN2U5MThkMA==",
                "followedEdges": {
                  "count": 0
                },
                "username": "maudie",
                "socialAccounts": {
                  "farcaster": null,
                  "twitter": null
                }
              }
            }
          },
          {
            "node": {
              "address": "0xcdb83fd58f648106794eb98198cfd5909124f70f",
              "name": "cypherbadger",
              "createdAt": "2025-07-27T21:43:57",
              "creatorProfile": {
                "id": "R3JhcGhRTEFjY291bnRQcm9maWxlOjY1NTkyZTg2YTczNmJlNTk4OGIxN2ViMQ==",
                "followedEdges": {
                  "count": 26
                },
                "username": "cypherbadger",
                "socialAccounts": {
                  "farcaster": null,
                  "twitter": null
                }
              }
            }
          },
          {
            "node": {
              "address": "0x6de06074525a9495fe5de313ac4358fa0684d612",
              "name": "jacob_baron",
              "createdAt": "2025-07-27T21:43:55",
              "creatorProfile": {
                "id": "R3JhcGhRTEFjY291bnRQcm9maWxlOjY4ODY5ZDdkOWMzYTM1NzNmYTBlY2ZjNw==",
                "followedEdges": {
                  "count": 0
                },
                "username": "jacob_baron",
                "socialAccounts": {
                  "farcaster": null,
                  "twitter": null
                }
              }
            }
          },
          {
            "node": {
              "address": "0x98a21a8d25e68d27287b80225026ae97558f5e5a",
              "name": "web3adri",
              "createdAt": "2025-07-27T21:43:55",
              "creatorProfile": {
                "id": "R3JhcGhRTEFjY291bnRQcm9maWxlOjY4ODY5ZDhkNmYzODRjMTE4ZWE3YWViOA==",
                "followedEdges": {
                  "count": 0
                },
                "username": "web3adri",
                "socialAccounts": {
                  "farcaster": null,
                  "twitter": null
                }
              }
            }
          },
          {
            "node": {
              "address": "0xa5005b69ee74ca2fb613fa87355f029781ea906f",
              "name": "mayden",
              "createdAt": "2025-07-27T21:43:47",
              "creatorProfile": {
                "id": "R3JhcGhRTEFjY291bnRQcm9maWxlOjY4ODY5ZDNkMzk0YTExOTQ3MWIzNTJmOQ==",
                "followedEdges": {
                  "count": 1
                },
                "username": "mayden",
                "socialAccounts": {
                  "farcaster": null,
                  "twitter": null
                }
              }
            }
          },
          {
            "node": {
              "address": "0x138579ad84c6f252fef70c943e2ab6278c2df6a4",
              "name": "johnna",
              "createdAt": "2025-07-27T21:43:37",
              "creatorProfile": {
                "id": "R3JhcGhRTEFjY291bnRQcm9maWxlOjY4ODY5ZDdhYmY1MjFkYmNhN2U5MThjZA==",
                "followedEdges": {
                  "count": 0
                },
                "username": "johnna",
                "socialAccounts": {
                  "farcaster": null,
                  "twitter": {
                    "displayName": "Johnna.eth",
                    "username": "jd_powell_"
                  }
                }
              }
            }
          },
          {
            "node": {
              "address": "0x93c467e09775dada3e05885e9f13e0f244dd081e",
              "name": "dracofenrir",
              "createdAt": "2025-07-27T21:43:35",
              "creatorProfile": {
                "id": "R3JhcGhRTEFjY291bnRQcm9maWxlOjY4ODY5ZDM4NDI2OGJjNjQwYzEwNjkxNw==",
                "followedEdges": {
                  "count": 0
                },
                "username": "dracofenrir",
                "socialAccounts": {
                  "farcaster": null,
                  "twitter": {
                    "displayName": "dracogrid",
                    "username": "Dracogrid"
                  }
                }
              }
            }
          },
          {
            "node": {
              "address": "0x954e74259e221c4f50781b05f0d90e113592c60f",
              "name": "sinapa",
              "createdAt": "2025-07-27T21:43:35",
              "creatorProfile": {
                "id": "R3JhcGhRTEFjY291bnRQcm9maWxlOjY4ODY5ZDVlYjc4M2E3ODhhNjI1MGY5NA==",
                "followedEdges": {
                  "count": 0
                },
                "username": "sinapa",
                "socialAccounts": {
                  "farcaster": null,
                  "twitter": null
                }
              }
            }
          },
          {
            "node": {
              "address": "0xfec24d32c2fee982186f5925e93503c7c5a032d3",
              "name": "ken_ny6202",
              "createdAt": "2025-07-27T21:43:33",
              "creatorProfile": {
                "id": "R3JhcGhRTEFjY291bnRQcm9maWxlOjY4ODY5ZDNhNDI2OGJjNjQwYzEwNjkxYg==",
                "followedEdges": {
                  "count": 0
                },
                "username": "ken_ny6202",
                "socialAccounts": {
                  "farcaster": null,
                  "twitter": {
                    "displayName": "Kenny🔺",
                    "username": "Ken_ny6202"
                  }
                }
              }
            }
          },
          {
            "node": {
              "address": "0xd2520f8c5df3b9c0fab95e570bfb0278a32de1f0",
              "name": "lexzzy",
              "createdAt": "2025-07-27T21:43:27",
              "creatorProfile": {
                "id": "R3JhcGhRTEFjY291bnRQcm9maWxlOjY1Y2MzYjFlMWViY2RjNjQzOTlhOWQyMg==",
                "followedEdges": {
                  "count": 2
                },
                "username": "lexzzy",
                "socialAccounts": {
                  "farcaster": null,
                  "twitter": {
                    "displayName": "Lexzzyfrost",
                    "username": "iamlexzzyfrost"
                  }
                }
              }
            }
          },
          {
            "node": {
              "address": "0xd02b9b9b352f64769874ab0ffbb3a87b8522036c",
              "name": "olorioba1",
              "createdAt": "2025-07-27T21:43:25",
              "creatorProfile": {
                "id": "R3JhcGhRTEFjY291bnRQcm9maWxlOjY4ODY5ZDZkMjI1YTE2MDc1ZmVjNzRjNg==",
                "followedEdges": {
                  "count": 0
                },
                "username": "olorioba1",
                "socialAccounts": {
                  "farcaster": null,
                  "twitter": null
                }
              }
            }
          },
          {
            "node": {
              "address": "0x6899186657512ee60b7a20b750be1644f345bbfe",
              "name": "0wn",
              "createdAt": "2025-07-27T21:43:19",
              "creatorProfile": {
                "id": "R3JhcGhRTEFjY291bnRQcm9maWxlOjY2MTZmZDg1MTIyOGE2MTg2OTgxN2RlNA==",
                "followedEdges": {
                  "count": 423
                },
                "username": "0wn",
                "socialAccounts": {
                  "farcaster": {
                    "displayName": "0x0 🎩🔵🍖",
                    "username": "0wn"
                  },
                  "twitter": {
                    "displayName": "sajoooni ❤️$WELL",
                    "username": "sajoooni"
                  }
                }
              }
            }
          },
          {
            "node": {
              "address": "0xa5c29339c029a3d369885ec8d00bc55e285753a2",
              "name": "chrismaddern",
              "createdAt": "2025-07-27T21:43:13",
              "creatorProfile": {
                "id": "R3JhcGhRTEFjY291bnRQcm9maWxlOjY1NjBhMTZmN2UwM2M2NDIzOWZlMDljNQ==",
                "followedEdges": {
                  "count": 117
                },
                "username": "chrismaddern",
                "socialAccounts": {
                  "farcaster": null,
                  "twitter": null
                }
              }
            }
          },
          {
            "node": {
              "address": "0x5cb0ec8fad53c0fd2ea199cf03c80fbb99ae7204",
              "name": "giorgiwanderer",
              "createdAt": "2025-07-27T21:43:13",
              "creatorProfile": {
                "id": "R3JhcGhRTEFjY291bnRQcm9maWxlOjY2OTA2NzM0N2MxOTY4ZjMwYjA4MmJlOA==",
                "followedEdges": {
                  "count": 12
                },
                "username": "giorgiwanderer",
                "socialAccounts": {
                  "farcaster": null,
                  "twitter": null
                }
              }
            }
          },
          {
            "node": {
              "address": "0x744fd7ce5e954768f7df79539e32992726ca92fc",
              "name": "zoripi",
              "createdAt": "2025-07-27T21:43:11",
              "creatorProfile": {
                "id": "R3JhcGhRTEFjY291bnRQcm9maWxlOjY4ODY5ZDVmYWQ2YzlhODUxZWRhN2ZjZA==",
                "followedEdges": {
                  "count": 0
                },
                "username": "zoripi",
                "socialAccounts": {
                  "farcaster": null,
                  "twitter": null
                }
              }
            }
          },
          {
            "node": {
              "address": "0x7cdb71e87b7e141b0f301867945210d17e44b069",
              "name": "tamrat",
              "createdAt": "2025-07-27T21:43:01",
              "creatorProfile": {
                "id": "R3JhcGhRTEFjY291bnRQcm9maWxlOjY1NjhhNzI4ZGIxODdlNTg2ZWJkYThjMQ==",
                "followedEdges": {
                  "count": 605
                },
                "username": "tamrat",
                "socialAccounts": {
                  "farcaster": {
                    "displayName": "Tamrat",
                    "username": "tamrat"
                  },
                  "twitter": {
                    "displayName": "tamrat",
                    "username": "tamrrat"
                  }
                }
              }
            }
          },
          {
            "node": {
              "address": "0xd4f9965ffabfb39e16144c6442a09c5f7a446c46",
              "name": "alizeegamberini",
              "createdAt": "2025-07-27T21:42:55",
              "creatorProfile": {
                "id": "R3JhcGhRTEFjY291bnRQcm9maWxlOjY4ODY5ZDUxYmE5MDJkZTUzNDY0YjczMQ==",
                "followedEdges": {
                  "count": 1
                },
                "username": "alizeegamberini",
                "socialAccounts": {
                  "farcaster": null,
                  "twitter": null
                }
              }
            }
          },
          {
            "node": {
              "address": "0xff68bdf71e423ac914dda7365d0c3d3743b3d041",
              "name": "lesizzle",
              "createdAt": "2025-07-27T21:42:55",
              "creatorProfile": {
                "id": "R3JhcGhRTEFjY291bnRQcm9maWxlOjY4ODY5ZDRjM2FmZjdjYTQ4ZDVhYjcxNQ==",
                "followedEdges": {
                  "count": 0
                },
                "username": "lesizzle",
                "socialAccounts": {
                  "farcaster": null,
                  "twitter": null
                }
              }
            }
          },
          {
            "node": {
              "address": "0xe19a8afdf653674e44cac4a55ce61bef7f1059ac",
              "name": "tuandudinh",
              "createdAt": "2025-07-27T21:42:55",
              "creatorProfile": {
                "id": "R3JhcGhRTEFjY291bnRQcm9maWxlOjY4ODY5ZDUxYjc4M2E3ODhhNjI1MGY5MQ==",
                "followedEdges": {
                  "count": 0
                },
                "username": "tuandudinh",
                "socialAccounts": {
                  "farcaster": null,
                  "twitter": {
                    "displayName": "Xuan Tuan Pham",
                    "username": "XuanTuanPham101"
                  }
                }
              }
            }
          },
          {
            "node": {
              "address": "0x038a6d368bfe50b262e2b9483f4aeade62c96e83",
              "name": "kita",
              "createdAt": "2025-07-27T21:42:49",
              "creatorProfile": {
                "id": "R3JhcGhRTEFjY291bnRQcm9maWxlOjY4ODY5Y2YyZDk1MGY0NTcwNjk2NTAzMg==",
                "followedEdges": {
                  "count": 0
                },
                "username": "kita",
                "socialAccounts": {
                  "farcaster": null,
                  "twitter": null
                }
              }
            }
          },
          {
            "node": {
              "address": "0xc5913e66347f1db68f83bfc3bb13ce8a66536586",
              "name": "ciskodisco",
              "createdAt": "2025-07-27T21:42:49",
              "creatorProfile": {
                "id": "R3JhcGhRTEFjY291bnRQcm9maWxlOjY2MDU0NGRjOTBiOWYyNWZmNzViZTE4Mg==",
                "followedEdges": {
                  "count": 14
                },
                "username": "ciskodisco",
                "socialAccounts": {
                  "farcaster": null,
                  "twitter": null
                }
              }
            }
          },
          {
            "node": {
              "address": "0x325832ac59f406067749307865b24ffe37ba8631",
              "name": "polside",
              "createdAt": "2025-07-27T21:42:29",
              "creatorProfile": {
                "id": "R3JhcGhRTEFjY291bnRQcm9maWxlOjY4ODY5ZDM1NDRhZGE0OGJlNmJmMjRjNQ==",
                "followedEdges": {
                  "count": 0
                },
                "username": "polside",
                "socialAccounts": {
                  "farcaster": null,
                  "twitter": null
                }
              }
            }
          },
          {
            "node": {
              "address": "0x0dd511133dbfa4b5b5ad55151516d521a2865cb0",
              "name": "luna_virtual",
              "createdAt": "2025-07-27T21:42:09",
              "creatorProfile": {
                "id": "R3JhcGhRTEFjY291bnRQcm9maWxlOjY4ODY5YzRkOWMzYTM1NzNmYTBlY2ZjMA==",
                "followedEdges": {
                  "count": 0
                },
                "username": "luna_virtual",
                "socialAccounts": {
                  "farcaster": {
                    "displayName": "Schaferr",
                    "username": "schaferrr"
                  },
                  "twitter": {
                    "displayName": "Schaferr",
                    "username": "GagasDuwi"
                  }
                }
              }
            }
          },
          {
            "node": {
              "address": "0x13b0f65c8a59514b3f218ffd90d3dd8044c32442",
              "name": "dexx",
              "createdAt": "2025-07-27T21:42:07",
              "creatorProfile": {
                "id": "R3JhcGhRTEFjY291bnRQcm9maWxlOjY4ODY5ZDFmZjQ4MjhlYjAzNmQ4ZWIyNQ==",
                "followedEdges": {
                  "count": 0
                },
                "username": "dexx",
                "socialAccounts": {
                  "farcaster": null,
                  "twitter": null
                }
              }
            }
          },
          {
            "node": {
              "address": "0x6bf6ca9a22d49a7d79f39ec4a46a43ae9df18f94",
              "name": "andy2021",
              "createdAt": "2025-07-27T21:42:05",
              "creatorProfile": {
                "id": "R3JhcGhRTEFjY291bnRQcm9maWxlOjY4ODY5ZDFlOWI0MTEyMmRjNzZjZjNkNA==",
                "followedEdges": {
                  "count": 0
                },
                "username": "andy2021",
                "socialAccounts": {
                  "farcaster": null,
                  "twitter": null
                }
              }
            }
          },
          {
            "node": {
              "address": "0x11dac89e81f42f42ed4ba4c090cb6558b024149e",
              "name": "xrock",
              "createdAt": "2025-07-27T21:41:59",
              "creatorProfile": {
                "id": "R3JhcGhRTEFjY291bnRQcm9maWxlOjY4ODY5ZDE1ODEyYWFhMTkyYTM1Y2VmYQ==",
                "followedEdges": {
                  "count": 0
                },
                "username": "xrock",
                "socialAccounts": {
                  "farcaster": null,
                  "twitter": null
                }
              }
            }
          },
          {
            "node": {
              "address": "0xf87b96983f16394cab3c6706b139a904acc3b4e9",
              "name": "kaffa",
              "createdAt": "2025-07-27T21:41:59",
              "creatorProfile": {
                "id": "R3JhcGhRTEFjY291bnRQcm9maWxlOjY4ODY5ZDE5ZWFhZTA0YmZkYTgwYmIzYw==",
                "followedEdges": {
                  "count": 0
                },
                "username": "kaffa",
                "socialAccounts": {
                  "farcaster": null,
                  "twitter": null
                }
              }
            }
          },
          {
            "node": {
              "address": "0x80ed9553359fa119a15687f3478ce7136d0fd378",
              "name": "qrcoind0tfun",
              "createdAt": "2025-07-27T21:41:59",
              "creatorProfile": {
                "id": "R3JhcGhRTEFjY291bnRQcm9maWxlOjY4ODY5ZDE3ZDk1MGY0NTcwNjk2NTAzNQ==",
                "followedEdges": {
                  "count": 0
                },
                "username": "qrcoind0tfun",
                "socialAccounts": {
                  "farcaster": null,
                  "twitter": null
                }
              }
            }
          },
          {
            "node": {
              "address": "0x3391e1ac88f99f832d7fd60dfc14c5d11b5eea95",
              "name": "sirsamjenks",
              "createdAt": "2025-07-27T21:41:59",
              "creatorProfile": {
                "id": "R3JhcGhRTEFjY291bnRQcm9maWxlOjY4ODY5ZDE4Yjc4M2E3ODhhNjI1MGY4ZQ==",
                "followedEdges": {
                  "count": 1
                },
                "username": "sirsamjenks",
                "socialAccounts": {
                  "farcaster": null,
                  "twitter": {
                    "displayName": "Sam Jenks",
                    "username": "sirsamjenks"
                  }
                }
              }
            }
          },
          {
            "node": {
              "address": "0x0b5eb3968c614b8867dbd0155ae349b131b74519",
              "name": "deployers",
              "createdAt": "2025-07-27T21:41:57",
              "creatorProfile": {
                "id": "R3JhcGhRTEFjY291bnRQcm9maWxlOjY4ODY5ZDEzYmE5MDJkZTUzNDY0YjcyZA==",
                "followedEdges": {
                  "count": 1
                },
                "username": "deployers",
                "socialAccounts": {
                  "farcaster": null,
                  "twitter": null
                }
              }
            }
          },
          {
            "node": {
              "address": "0x169095178f1db6556d155b613c08f3a5870facad",
              "name": "tom77",
              "createdAt": "2025-07-27T21:41:57",
              "creatorProfile": {
                "id": "R3JhcGhRTEFjY291bnRQcm9maWxlOjY4MDkyMTk3ZDFlZDY5MjVhM2Q4ZWZjMw==",
                "followedEdges": {
                  "count": 0
                },
                "username": "tom77",
                "socialAccounts": {
                  "farcaster": null,
                  "twitter": null
                }
              }
            }
          },
          {
            "node": {
              "address": "0x6875262573efa3447bdee8e9b57ba345ec29e561",
              "name": "taksvj",
              "createdAt": "2025-07-27T21:41:49",
              "creatorProfile": {
                "id": "R3JhcGhRTEFjY291bnRQcm9maWxlOjY3NTUzZWUyMTFmN2U0NTY0ZGU0NWJjYg==",
                "followedEdges": {
                  "count": 21
                },
                "username": "taksvj",
                "socialAccounts": {
                  "farcaster": {
                    "displayName": "Audrey",
                    "username": "taksvj"
                  },
                  "twitter": {
                    "displayName": "Taksvj CLONE",
                    "username": "taksvj"
                  }
                }
              }
            }
          },
          {
            "node": {
              "address": "0x61d60e6977381b1bee46841532ba13faca855995",
              "name": "deslucrece",
              "createdAt": "2025-07-27T21:41:39",
              "creatorProfile": {
                "id": "R3JhcGhRTEFjY291bnRQcm9maWxlOjY4ODY5Y2ZkOWI0MTEyMmRjNzZjZjNkMQ==",
                "followedEdges": {
                  "count": 0
                },
                "username": "deslucrece",
                "socialAccounts": {
                  "farcaster": null,
                  "twitter": null
                }
              }
            }
          },
          {
            "node": {
              "address": "0xc4383a1da4bc25a89cb00126eb973062ece793a3",
              "name": "coolguy_2000",
              "createdAt": "2025-07-27T21:41:29",
              "creatorProfile": {
                "id": "R3JhcGhRTEFjY291bnRQcm9maWxlOjY4ODY5Y2ZjZmZlMzczM2ZlNTQyYWM4Mg==",
                "followedEdges": {
                  "count": 0
                },
                "username": "coolguy_2000",
                "socialAccounts": {
                  "farcaster": null,
                  "twitter": null
                }
              }
            }
          },
          {
            "node": {
              "address": "0xe8c09edec0d78e66c790a606db1b628a589f6c4c",
              "name": "drewfromweb3",
              "createdAt": "2025-07-27T21:41:27",
              "creatorProfile": {
                "id": "R3JhcGhRTEFjY291bnRQcm9maWxlOjY4ODY5Y2ZhODEyYWFhMTkyYTM1Y2VmNg==",
                "followedEdges": {
                  "count": 0
                },
                "username": "drewfromweb3",
                "socialAccounts": {
                  "farcaster": null,
                  "twitter": null
                }
              }
            }
          },
          {
            "node": {
              "address": "0xa7a1fb249b7b480a75c8b2f44949b11dc538d651",
              "name": "arewadata1",
              "createdAt": "2025-07-27T21:41:25",
              "creatorProfile": {
                "id": "R3JhcGhRTEFjY291bnRQcm9maWxlOjY3YzcwNDI0MTU2MTI5ODY5MTJmZmM1Zg==",
                "followedEdges": {
                  "count": 13
                },
                "username": "arewadata1",
                "socialAccounts": {
                  "farcaster": null,
                  "twitter": {
                    "displayName": "Haruna Ishaq",
                    "username": "HarunaIsha9809"
                  }
                }
              }
            }
          },
          {
            "node": {
              "address": "0xc56c3f871df10167c8aa00a1d00040bed1c5b17c",
              "name": "pikapika1984",
              "createdAt": "2025-07-27T21:41:23",
              "creatorProfile": {
                "id": "R3JhcGhRTEFjY291bnRQcm9maWxlOjY1MzQyOGNjM2Y5NDdjZmEwMTNmNzc5Zg==",
                "followedEdges": {
                  "count": 252
                },
                "username": "pikapika1984",
                "socialAccounts": {
                  "farcaster": {
                    "displayName": "Pika",
                    "username": "pikapika1984"
                  },
                  "twitter": {
                    "displayName": "pikapika1984",
                    "username": "Pikapika1984r"
                  }
                }
              }
            }
          },
          {
            "node": {
              "address": "0xa189b3b3e75f0b4b3df77c715c3534c8c27ca406",
              "name": "noori2",
              "createdAt": "2025-07-27T21:41:01",
              "creatorProfile": {
                "id": "R3JhcGhRTEFjY291bnRQcm9maWxlOjY1NzE5MThhYWI1YWNlMjZiMzk5NTFiNQ==",
                "followedEdges": {
                  "count": 215
                },
                "username": "noori2",
                "socialAccounts": {
                  "farcaster": null,
                  "twitter": null
                }
              }
            }
          },
          {
            "node": {
              "address": "0x324ee1c65756be3fb7e18dfa42ddd415ba315f1a",
              "name": "xebidiah",
              "createdAt": "2025-07-27T21:40:51",
              "creatorProfile": {
                "id": "R3JhcGhRTEFjY291bnRQcm9maWxlOjY3MGQ3YTI0NGJiOWM3NmFiMzM2ZDYwMQ==",
                "followedEdges": {
                  "count": 30
                },
                "username": "xebidiah",
                "socialAccounts": {
                  "farcaster": null,
                  "twitter": null
                }
              }
            }
          },
          {
            "node": {
              "address": "0x5fd666e975091aaa8ffffe04ded85741d8db419e",
              "name": "poolside",
              "createdAt": "2025-07-27T21:40:47",
              "creatorProfile": {
                "id": "R3JhcGhRTEFjY291bnRQcm9maWxlOjY4ODY5Y2NkYjc4M2E3ODhhNjI1MGY4Yg==",
                "followedEdges": {
                  "count": 0
                },
                "username": "poolside",
                "socialAccounts": {
                  "farcaster": null,
                  "twitter": null
                }
              }
            }
          },
          {
            "node": {
              "address": "0xb59e9e3dc6e5cc230d09c7aaa18ee730d6c99043",
              "name": "shaye",
              "createdAt": "2025-07-27T21:40:29",
              "creatorProfile": {
                "id": "R3JhcGhRTEFjY291bnRQcm9maWxlOjY4ODY5Y2MwYjc4M2E3ODhhNjI1MGY4OA==",
                "followedEdges": {
                  "count": 0
                },
                "username": "shaye",
                "socialAccounts": {
                  "farcaster": null,
                  "twitter": null
                }
              }
            }
          },
          {
            "node": {
              "address": "0x420d6e61ddcfdc5f44e88e424b9ffaabaef845e1",
              "name": "electricbyzora",
              "createdAt": "2025-07-27T21:40:25",
              "creatorProfile": {
                "id": "R3JhcGhRTEFjY291bnRQcm9maWxlOjY4ODY5Yzc3YmY1MjFkYmNhN2U5MThjOQ==",
                "followedEdges": {
                  "count": 2
                },
                "username": "electricbyzora",
                "socialAccounts": {
                  "farcaster": null,
                  "twitter": null
                }
              }
            }
          },
          {
            "node": {
              "address": "0xaf07c2fb0f05f9ea61c0f27926212f7b3b261134",
              "name": "bbn00001",
              "createdAt": "2025-07-27T21:40:25",
              "creatorProfile": {
                "id": "R3JhcGhRTEFjY291bnRQcm9maWxlOjY4ODY5YzllZGVhN2Q1MzkxOGU4YWJiMQ==",
                "followedEdges": {
                  "count": 1
                },
                "username": "bbn00001",
                "socialAccounts": {
                  "farcaster": null,
                  "twitter": null
                }
              }
            }
          },
          {
            "node": {
              "address": "0xec2b38b165b3544d6ddfa4364ca6c846b848c23c",
              "name": "justsh1t",
              "createdAt": "2025-07-27T21:40:21",
              "creatorProfile": {
                "id": "R3JhcGhRTEFjY291bnRQcm9maWxlOjY2MTU5OTAxM2RkNjAwYmE0NjRlNzkxZg==",
                "followedEdges": {
                  "count": 7
                },
                "username": "justsh1t",
                "socialAccounts": {
                  "farcaster": null,
                  "twitter": null
                }
              }
            }
          },
          {
            "node": {
              "address": "0x957d64fb4bcef2fc91a0b10ed81bb8e937c10301",
              "name": "designerr",
              "createdAt": "2025-07-27T21:40:09",
              "creatorProfile": {
                "id": "R3JhcGhRTEFjY291bnRQcm9maWxlOjY4ODY5Yzk0NDI2OGJjNjQwYzEwNjkxMQ==",
                "followedEdges": {
                  "count": 1
                },
                "username": "designerr",
                "socialAccounts": {
                  "farcaster": null,
                  "twitter": null
                }
              }
            }
          },
          {
            "node": {
              "address": "0xa78a4e6ccc47b128b32bc574c805689b7bedd69f",
              "name": "lamaaboo",
              "createdAt": "2025-07-27T21:40:05",
              "creatorProfile": {
                "id": "R3JhcGhRTEFjY291bnRQcm9maWxlOjY4ODY5Yzg2MjI1YTE2MDc1ZmVjNzRiZQ==",
                "followedEdges": {
                  "count": 2
                },
                "username": "lamaaboo",
                "socialAccounts": {
                  "farcaster": null,
                  "twitter": null
                }
              }
            }
          },
          {
            "node": {
              "address": "0x952869613badb03d097a0a2e1be096b49dc1b594",
              "name": "basetoken",
              "createdAt": "2025-07-27T21:40:03",
              "creatorProfile": {
                "id": "R3JhcGhRTEFjY291bnRQcm9maWxlOjY4ODY5YzljNDRhZGE0OGJlNmJmMjRjMg==",
                "followedEdges": {
                  "count": 0
                },
                "username": "basetoken",
                "socialAccounts": {
                  "farcaster": null,
                  "twitter": null
                }
              }
            }
          },
          {
            "node": {
              "address": "0x140554e3a7d61a0167f82be314fd60b2e4839abd",
              "name": "zduck",
              "createdAt": "2025-07-27T21:40:01",
              "creatorProfile": {
                "id": "R3JhcGhRTEFjY291bnRQcm9maWxlOjY4ODY5Yzk5OTYwMDRhYWU5ODU3YTNkMg==",
                "followedEdges": {
                  "count": 0
                },
                "username": "zduck",
                "socialAccounts": {
                  "farcaster": null,
                  "twitter": null
                }
              }
            }
          },
          {
            "node": {
              "address": "0xbb44ec707c94f6425320785f9e067210fac72e94",
              "name": "yfndx",
              "createdAt": "2025-07-27T21:39:55",
              "creatorProfile": {
                "id": "R3JhcGhRTEFjY291bnRQcm9maWxlOjY4ODY5YzkwMzk0YTExOTQ3MWIzNTJmMw==",
                "followedEdges": {
                  "count": 0
                },
                "username": "yfndx",
                "socialAccounts": {
                  "farcaster": null,
                  "twitter": null
                }
              }
            }
          },
          {
            "node": {
              "address": "0xbb069c8c4ce1d9f2665ff0b59543828784554bd1",
              "name": "cryptogodjake",
              "createdAt": "2025-07-27T21:39:43",
              "creatorProfile": {
                "id": "R3JhcGhRTEFjY291bnRQcm9maWxlOjY4ODY5YzkxYjc4M2E3ODhhNjI1MGY4NQ==",
                "followedEdges": {
                  "count": 0
                },
                "username": "cryptogodjake",
                "socialAccounts": {
                  "farcaster": null,
                  "twitter": null
                }
              }
            }
          }
        ]
      }
    }
  }